{
    "title": "28 - Cultural Identity in a Globalized World",
    "description": "دو نفر درباره اینکه آیا جهانی‌شدن فرهنگ‌های محلی را همگن می‌کند یا غنی‌تر تأمل می‌کنند.",
    "words": ["homogenize", "heritage", "preserve", "diversity", "assimilation", "authentic", "erode", "hybrid", "tradition", "globalized", "resilient", "distinct", "enrich", "dilute"],
    "sentences": [
        {
            "order": 0,
            "person": 1,
            "text": "Do you think globalization erases local cultures?",
            "translation": "فکر می‌کنی جهانی‌شدن فرهنگ‌های محلی را پاک می‌کند؟"
        },
        {
            "order": 1,
            "person": 2,
            "text": "Partly, but it also creates new hybrids.",
            "translation": "تا حدی، اما ترکیب‌های جدیدی هم می‌سازد."
        },
        {
            "order": 2,
            "person": 1,
            "text": "Still, so much feels homogenized now.",
            "translation": "با این حال، حالا خیلی چیزها همگن به نظر می‌رسند."
        },
        {
            "order": 3,
            "person": 2,
            "text": "The same brands everywhere, you mean?",
            "translation": "منظورت برندهای یکسان در همه‌جاست؟"
        },
        {
            "order": 4,
            "person": 1,
            "text": "Yes. Distinct traditions seem to fade.",
            "translation": "بله. سنت‌های متمایز انگار محو می‌شوند."
        },
        {
            "order": 5,
            "person": 2,
            "text": "Yet many communities fiercely preserve theirs.",
            "translation": "با این حال خیلی جوامع به‌شدت از مال خود حفاظت می‌کنند."
        },
        {
            "order": 6,
            "person": 1,
            "text": "True. Identity can be remarkably resilient.",
            "translation": "درست است. هویت می‌تواند به‌طرز چشمگیری تاب‌آور باشد."
        },
        {
            "order": 7,
            "person": 2,
            "text": "And exposure can enrich rather than dilute.",
            "translation": "و مواجهه می‌تواند غنی کند نه اینکه رقیق کند."
        },
        {
            "order": 8,
            "person": 1,
            "text": "So it's not purely a loss?",
            "translation": "پس صرفاً یک باخت نیست؟"
        },
        {
            "order": 9,
            "person": 2,
            "text": "No, cultures have always borrowed and evolved.",
            "translation": "نه، فرهنگ‌ها همیشه وام گرفته و تکامل یافته‌اند."
        },
        {
            "order": 10,
            "person": 1,
            "text": "The key is preserving what's authentic.",
            "translation": "نکته کلیدی حفظ آنچه اصیل است."
        },
        {
            "order": 11,
            "person": 2,
            "text": "While remaining open to the world.",
            "translation": "در عین حال باز ماندن به روی جهان."
        }
    ]
}
