{
    "title": "36 - Talking About Pets",
    "description": "دو همکار درباره حیوانات خانگی‌شان صحبت می‌کنند.",
    "words": [
        "pet",
        "cat",
        "dog",
        "feed",
        "walk",
        "playful",
        "fur",
        "responsibility",
        "vet",
        "rescue",
        "company",
        "adopt",
        "love"
    ],
    "estimatedDuration": 1,
    "sentences": [
        {
            "order": 0,
            "person": 1,
            "text": "Do you have any pets?",
            "translation": "حیوان خانگی داری؟"
        },
        {
            "order": 1,
            "person": 2,
            "text": "Yes, I have a cat and a dog.",
            "translation": "بله، یک گربه و یک سگ دارم."
        },
        {
            "order": 2,
            "person": 1,
            "text": "That's lovely. Are they playful?",
            "translation": "چه خوب. بازیگوش هستند؟"
        },
        {
            "order": 3,
            "person": 2,
            "text": "The dog is, but the cat is quiet.",
            "translation": "سگ هست، اما گربه آرام است."
        },
        {
            "order": 4,
            "person": 1,
            "text": "Do you walk the dog every day?",
            "translation": "هر روز سگ را به پیاده‌روی می‌بری؟"
        },
        {
            "order": 5,
            "person": 2,
            "text": "Yes, twice a day. It's a big responsibility.",
            "translation": "بله، روزی دو بار. مسئولیت بزرگی است."
        },
        {
            "order": 6,
            "person": 1,
            "text": "Where did you get them?",
            "translation": "آن‌ها را از کجا گرفتی؟"
        },
        {
            "order": 7,
            "person": 2,
            "text": "I adopted them from a rescue center.",
            "translation": "از یک مرکز نگهداری حیوانات به سرپرستی گرفتم."
        },
        {
            "order": 8,
            "person": 1,
            "text": "That's wonderful. They must be happy.",
            "translation": "فوق‌العاده است. حتماً خوشحالند."
        },
        {
            "order": 9,
            "person": 2,
            "text": "They are. They give me great company.",
            "translation": "هستند. همدم خیلی خوبی برایم هستند."
        },
        {
            "order": 10,
            "person": 1,
            "text": "Maybe I should adopt a pet too.",
            "translation": "شاید من هم باید یک حیوان خانگی بگیرم."
        },
        {
            "order": 11,
            "person": 2,
            "text": "You should! They bring so much love.",
            "translation": "حتماً بگیر! کلی محبت می‌آورند."
        }
    ]
}
